primefac/__init__.py
primefac/__main__.py
primefac/primefac.py
primefac-2.0.11.dist-info/LICENSE
primefac-2.0.11.dist-info/METADATA
primefac-2.0.11.dist-info/WHEEL
primefac-2.0.11.dist-info/top_level.txt
primefac-2.0.11.dist-info/RECORD
